braindrop/__init__.py
braindrop/__main__.py
braindrop/app/__init__.py
braindrop/app/braindrop.py
braindrop/app/commands/__init__.py
braindrop/app/commands/collection.py
braindrop/app/commands/filtering.py
braindrop/app/commands/main.py
braindrop/app/commands/raindrop.py
braindrop/app/data/__init__.py
braindrop/app/data/config.py
braindrop/app/data/exit_state.py
braindrop/app/data/local.py
braindrop/app/data/locations.py
braindrop/app/data/raindrops.py
braindrop/app/data/token.py
braindrop/app/messages/__init__.py
braindrop/app/messages/main.py
braindrop/app/providers/__init__.py
braindrop/app/providers/collections.py
braindrop/app/providers/main.py
braindrop/app/providers/tags.py
braindrop/app/screens/__init__.py
braindrop/app/screens/downloading.py
braindrop/app/screens/main.py
braindrop/app/screens/raindrop_input.py
braindrop/app/screens/token_input.py
braindrop/app/screens/wayback_checker.py
braindrop/app/suggestions/__init__.py
braindrop/app/suggestions/tags.py
braindrop/app/widgets/__init__.py
braindrop/app/widgets/icons.py
braindrop/app/widgets/navigation.py
braindrop/app/widgets/raindrop_details.py
braindrop/app/widgets/raindrops_view.py
braindrop/py.typed
braindrop/raindrop/__init__.py
braindrop/raindrop/api.py
braindrop/raindrop/collection.py
braindrop/raindrop/raindrop.py
braindrop/raindrop/suggestions.py
braindrop/raindrop/tag.py
braindrop/raindrop/time_tools.py
braindrop/raindrop/user.py
braindrop/wayback/__init__.py
braindrop/wayback/api.py
braindrop-1.0.0.dist-info/WHEEL
braindrop-1.0.0.dist-info/entry_points.txt
braindrop-1.0.0.dist-info/METADATA
braindrop-1.0.0.dist-info/RECORD
