Metadata-Version: 2.4
Name: braindrop
Version: 1.0.0
Summary: A terminal-based client for raindrop.io.
Keywords: bookmark,bookmarking,terminal,raindrop,raindrop.io,tui,chui
Author: Dave Pearson
Author-email: Dave Pearson <davep@davep.org>
License-Expression: GPL-3.0-or-later
Classifier: Development Status :: 5 - Production/Stable
Classifier: Environment :: Console
Classifier: Intended Audience :: End Users/Desktop
Classifier: Natural Language :: English
Classifier: Operating System :: OS Independent
Classifier: Programming Language :: Python :: 3 :: Only
Classifier: Programming Language :: Python :: 3
Classifier: Programming Language :: Python :: 3.12
Classifier: Programming Language :: Python :: 3.13
Classifier: Programming Language :: Python :: 3.14
Classifier: Programming Language :: Python :: 3.15
Classifier: Topic :: Internet
Classifier: Topic :: Terminals
Classifier: Topic :: Utilities
Classifier: Typing :: Typed
Requires-Dist: httpx>=0.27.2
Requires-Dist: textual>=6.6
Requires-Dist: xdg-base-dirs>=6.0.2
Requires-Dist: pytz>=2024.2
Requires-Dist: humanize>=4.11.0
Requires-Dist: pyperclip>=1.9.0
Requires-Dist: typing-extensions>=4.12.2
Requires-Dist: textual-enhanced>=1.0.0
Requires-Python: >=3.12
Project-URL: Discussions, https://github.com/davep/braindrop/discussions
Project-URL: Documentation, https://github.com/davep/braindrop/blob/main/README.md
Project-URL: Homepage, https://github.com/davep/braindrop
Project-URL: Issues, https://github.com/davep/braindrop/issues
Project-URL: Repository, https://github.com/davep/braindrop
Project-URL: Source, https://github.com/davep/braindrop
